AUTHORS
COPYING
ChangeLog
INSTALL.md
MANIFEST.in
README.md
VERSION
install_data.py
pyqt_setuptools.py
run_veusz_inplace
setup.cfg
setup.py
Documents/Makefile
Documents/man-page/veusz.1
Documents/man-page/veusz.man.txt
Documents/man-page/veusz.pod
Documents/manual/.gitignore
Documents/manual-source/Makefile
Documents/manual-source/api.rst
Documents/manual-source/conf.py
Documents/manual-source/datasets.rst
Documents/manual-source/index.rst
Documents/manual-source/introduction.rst
Documents/manual-source/make.bat
Documents/manual-source/_images/createdataset.png
Documents/manual-source/_images/customdefinition.png
Documents/manual-source/_images/defaultstyles.png
Documents/manual-source/_images/importdialog.png
Documents/manual-source/_images/importdialog_clipboard.png
Documents/manual-source/_images/mainwindow.png
Documents/manual-source/_images/winwithgraph.png
Documents/manual-source/_static/.gitignore
Documents/manual-source/_templates/.gitignore
Documents/manual/html/.buildinfo
Documents/manual/html/api.html
Documents/manual/html/datasets.html
Documents/manual/html/genindex.html
Documents/manual/html/index.html
Documents/manual/html/introduction.html
Documents/manual/html/objects.inv
Documents/manual/html/search.html
Documents/manual/html/searchindex.js
Documents/manual/html/_images/createdataset.png
Documents/manual/html/_images/customdefinition.png
Documents/manual/html/_images/importdialog.png
Documents/manual/html/_images/importdialog_clipboard.png
Documents/manual/html/_images/mainwindow.png
Documents/manual/html/_images/winwithgraph.png
Documents/manual/html/_sources/api.rst.txt
Documents/manual/html/_sources/datasets.rst.txt
Documents/manual/html/_sources/index.rst.txt
Documents/manual/html/_sources/introduction.rst.txt
Documents/manual/html/_static/alabaster.css
Documents/manual/html/_static/basic.css
Documents/manual/html/_static/custom.css
Documents/manual/html/_static/doctools.js
Documents/manual/html/_static/documentation_options.js
veusz.egg-info/PKG-INFO
veusz.egg-info/SOURCES.txt
veusz.egg-info/dependency_links.txt
veusz.egg-info/entry_points.txt
veusz.egg-info/requires.txt
veusz.egg-info/top_level.txt
