Metadata-Version: 2.1
Name: veusz
Version: 4.2
Summary: A scientific plotting package
Home-page: https://veusz.github.io/
Author: Jeremy Sanders
Author-email: jeremy@jeremysanders.net
License: GPL-2.0-or-later
Classifier: Programming Language :: Python
Classifier: Programming Language :: Python :: 3.8
Classifier: Programming Language :: Python :: 3.9
Classifier: Programming Language :: Python :: 3.10
Classifier: Programming Language :: Python :: 3.11
Classifier: Programming Language :: Python :: 3.12
Classifier: Programming Language :: Python :: 3.13
Classifier: Development Status :: 5 - Production/Stable
Classifier: Environment :: X11 Applications :: Qt
Classifier: Intended Audience :: Science/Research
Classifier: License :: OSI Approved :: GNU General Public License v2 or later (GPLv2+)
Classifier: Topic :: Scientific/Engineering :: Visualization
Provides-Extra: emf
Provides-Extra: fits
Provides-Extra: fitting
Provides-Extra: hdf5
License-File: COPYING
License-File: AUTHORS
